rgevolve/wet_4/flavio/__init__.py
rgevolve/wet_4/flavio/_version.py
rgevolve/wet_4/flavio/data.h5
rgevolve_wet_4_flavio-0.1.1.dist-info/licenses/LICENSE
rgevolve_wet_4_flavio-0.1.1.dist-info/METADATA
rgevolve_wet_4_flavio-0.1.1.dist-info/WHEEL
rgevolve_wet_4_flavio-0.1.1.dist-info/top_level.txt
rgevolve_wet_4_flavio-0.1.1.dist-info/RECORD
